mcp_server/__init__.py
mcp_server/server.py
mcp_server_botak-0.1.4.dist-info/METADATA
mcp_server_botak-0.1.4.dist-info/WHEEL
mcp_server_botak-0.1.4.dist-info/entry_points.txt
mcp_server_botak-0.1.4.dist-info/RECORD
