Metadata-Version: 2.4
Name: mcp-server-botak
Version: 0.1.4
Summary: Newest MCP Server Botak Release
Requires-Python: >=3.12
Requires-Dist: chromadb>=1.0.12
Requires-Dist: colorama>=0.4.6
Requires-Dist: mcp[cli]>=1.9.3
Requires-Dist: smolagents[litellm,mcp]>=1.18.0
Requires-Dist: yfinance>=0.2.62
